[{"Rank":"C","Fighter":"Jamahal Hill","Record":"12\u20131 (1 NC)","M":"","Win Streak":"4 (0 def)","Last Result":"Win","Last Event":"UFC 283","Last Opp":"Glover Teixeira","Next Event":"TBD","Next Opp":"TBD"},{"Rank":"1","Fighter":"Ji\u0159\u00ed Proch\u00e1zka","Record":"29\u20133\u20131","M":"","Win Streak":"13","Last Result":"Win","Last Event":"UFC 275","Last Opp":"Glover Teixeira","Next Event":"TBD","Next Opp":"TBD"},{"Rank":"2","Fighter":"Magomed Ankalaev","Record":"18\u20131\u20131","M":"","Win Streak":"0","Last Result":"Draw","Last Event":"UFC 282","Last Opp":"Jan B\u0142achowicz","Next Event":"TBD","Next Opp":"TBD"},{"Rank":"3","Fighter":"Jan B\u0142achowicz","Record":"29\u20139\u20131","M":"","Win Streak":"0","Last Result":"Draw","Last Event":"UFC 282","Last Opp":"Magomed Ankalaev","Next Event":"TBD","Next Opp":"TBD"},{"Rank":"4","Fighter":"Aleksandar Raki\u0107","Record":"14\u20133","M":"","Win Streak":"0","Last Result":"Loss","Last Event":"UFC on ESPN 36","Last Opp":"Jan B\u0142achowicz","Next Event":"TBD","Next Opp":"TBD"},{"Rank":"5","Fighter":"Anthony Smith","Record":"36\u201317","M":"","Win Streak":"0","Last Result":"Loss","Last Event":"UFC 277","Last Opp":"Magomed Ankalaev","Next Event":"UFC Fight Night 224","Next Opp":"Johnny Walker"},{"Rank":"6","Fighter":"Nikita Krylov","Record":"30\u20139","M":"","Win Streak":"3","Last Result":"Win","Last Event":"UFC Fight Night 221","Last Opp":"Ryan Spann","Next Event":"TBD","Next Opp":"TBD"},{"Rank":"7","Fighter":"Johnny Walker","Record":"20\u20137","M":"","Win Streak":"2","Last Result":"Win","Last Event":"UFC 283","Last Opp":"Paul Craig","Next Event":"UFC Fight Night 224","Next Opp":"Anthony Smith"},{"Rank":"8","Fighter":"Volkan Oezdemir","Record":"18\u20137","M":"","Win Streak":"0","Last Result":"Loss","Last Event":"UFC 280","Last Opp":"Nikita Krylov","Next Event":"TBD","Next Opp":"TBD"},{"Rank":"9","Fighter":"Paul Craig","Record":"16\u20136\u20131","M":"","Win Streak":"0","Last Result":"Loss","Last Event":"UFC 283","Last Opp":"Johnny Walker","Next Event":"TBD","Next Opp":"TBD"},{"Rank":"10","Fighter":"Ryan Spann","Record":"21\u20138","M":"","Win Streak":"0","Last Result":"Loss","Last Event":"UFC Fight Night 221","Last Opp":"Nikita Krylov","Next Event":"TBD","Next Opp":"TBD"},{"Rank":"11","Fighter":"Dominick Reyes","Record":"12\u20134","M":"","Win Streak":"0","Last Result":"Loss","Last Event":"UFC 281","Last Opp":"Ryan Spann","Next Event":"TBD","Next Opp":"TBD"},{"Rank":"12","Fighter":"Jimmy Crute","Record":"12\u20133\u20131","M":"","Win Streak":"0","Last Result":"Draw","Last Event":"UFC 284","Last Opp":"Alonzo Menifield","Next Event":"TBD","Next Opp":"TBD"},{"Rank":"13 (T)","Fighter":"Khalil Rountree Jr.","Record":"11\u20135 (1 NC)","M":"","Win Streak":"3","Last Result":"Win","Last Event":"UFC Fight Night 213","Last Opp":"Dustin Jacoby","Next Event":"TBD","Next Opp":"TBD"},{"Rank":"13 (T)","Fighter":"Dustin Jacoby","Record":"18\u20136\u20131","M":"","Win Streak":"0","Last Result":"Loss","Last Event":"UFC Fight Night 213","Last Opp":"Khalil Rountree Jr.","Next Event":"UFC on ESPN 44","Next Opp":"Azamat Murzakanov"},{"Rank":"15","Fighter":"Azamat Murzakanov","Record":"12\u20130","M":"","Win Streak":"12","Last Result":"Win","Last Event":"UFC on ESPN 41","Last Opp":"Devin Clark","Next Event":"UFC on ESPN 44","Next Opp":"Dustin Jacoby"}]