[{"Rank":"C","Fighter":"Dricus du Plessis","Record":"22\u20132","M":"","WinStreak":"10 (1 def)","ImageLink":"https:\/\/dmxg5wxfqgb4u.cloudfront.net\/styles\/athlete_bio_full_body\/s3\/2021-07\/DU_PLESSUS_DRICUS_L_07-10.png?itok=QK0-grkj"},{"Rank":"1","Fighter":"Sean Strickland","Record":"29\u20136","M":"","WinStreak":"1","ImageLink":""},{"Rank":"2","Fighter":"Israel Adesanya","Record":"24\u20134","M":"","WinStreak":"0","ImageLink":""},{"Rank":"3","Fighter":"Robert Whittaker","Record":"26\u20137","M":"","WinStreak":"2","ImageLink":""},{"Rank":"4","Fighter":"Nassourdine Imavov","Record":"14\u20134 (1 NC)","M":"","WinStreak":"2","ImageLink":""},{"Rank":"5","Fighter":"Jared Cannonier","Record":"17\u20138","M":"","WinStreak":"0","ImageLink":""},{"Rank":"6","Fighter":"Marvin Vettori","Record":"19\u20137\u20131","M":"","WinStreak":"0","ImageLink":""},{"Rank":"7","Fighter":"Brendan Allen","Record":"24\u20135","M":"","WinStreak":"7","ImageLink":""},{"Rank":"8","Fighter":"Paulo Costa","Record":"14\u20134","M":"","WinStreak":"0","ImageLink":""},{"Rank":"9","Fighter":"Jack Hermansson","Record":"24\u20138","M":"","WinStreak":"1","ImageLink":""},{"Rank":"10","Fighter":"Roman Dolidze","Record":"13\u20133","M":"","WinStreak":"1","ImageLink":""},{"Rank":"11","Fighter":"Khamzat Chimaev","Record":"13\u20130","M":"","WinStreak":"13","ImageLink":""},{"Rank":"12","Fighter":"Caio Borralho","Record":"17\u20131 (1 NC)","M":"","WinStreak":"14","ImageLink":""},{"Rank":"13","Fighter":"Michel Pereira","Record":"31\u201311 (2 NC)","M":"","WinStreak":"8","ImageLink":""},{"Rank":"14","Fighter":"Anthony Hernandez","Record":"12\u20132 (1 NC)","M":"","WinStreak":"5","ImageLink":""},{"Rank":"15","Fighter":"Chris Curtis","Record":"31\u201311 (1 NC)","M":"","WinStreak":"0","ImageLink":""}]